README.md
setup.py
mmtoolkit/__init__.py
mmtoolkit.egg-info/PKG-INFO
mmtoolkit.egg-info/SOURCES.txt
mmtoolkit.egg-info/dependency_links.txt
mmtoolkit.egg-info/not-zip-safe
mmtoolkit.egg-info/requires.txt
mmtoolkit.egg-info/top_level.txt
mmtoolkit/dehfa/__init__.py
mmtoolkit/dehfa/getEuler.py
mmtoolkit/io/__init__.py
mmtoolkit/io/ginp.py
mmtoolkit/io/io.py
mmtoolkit/io/vtkwriter.py
mmtoolkit/numbajit/__init__.py
mmtoolkit/numbajit/mori.py
mmtoolkit/plots/__init__.py
mmtoolkit/plots/plots.py
mmtoolkit/rotation/__init__.py
mmtoolkit/rotation/mori.py
mmtoolkit/rotation/rotationlib.py
mmtoolkit/segmentation/__init__.py
mmtoolkit/segmentation/slicer.py
mmtoolkit/stats/__init__.py
mmtoolkit/stats/optht.py
mmtoolkit/stats/pca.py
mmtoolkit/stats/regression.py
mmtoolkit/stats/spatialcorr.py
mmtoolkit/synthetic/__init__.py
mmtoolkit/synthetic/find.py