Metadata-Version: 2.1
Name: mmtoolkit
Version: 0.0.2
Summary: Microstructure-based Modelling Toolkit
Home-page: https://gitee.com/weeshin/mmtoolkit
Author: Wang, Xin
Author-email: xin.wang.418@aliyun.com
License: GPLv3
Platform: UNKNOWN
Requires-Python: >=3.5, <4
